topofileformats/__init__.py
topofileformats/asd.py
topofileformats/io.py
topofileformats-0.1.0.dist-info/LICENSE.md
topofileformats-0.1.0.dist-info/METADATA
topofileformats-0.1.0.dist-info/WHEEL
topofileformats-0.1.0.dist-info/top_level.txt
topofileformats-0.1.0.dist-info/RECORD
