Metadata-Version: 2.1
Name: topofileformats
Version: 0.1.0
Summary: Read and retrieve data from various AFM file formats.
Author-email: Sylvia Whittle <sylviwhittle@gmail.com>
Project-URL: Homepage, https://github.com/AFM-SPM/topofileformats
Project-URL: Bug Tracker, https://github.com/AFM-SPM/topofileformats/issues
Classifier: Development Status :: 3 - Alpha
Classifier: License :: OSI Approved :: GNU Lesser General Public License v3 (LGPLv3)
Classifier: Natural Language :: English
Classifier: Operating System :: OS Independent
Classifier: Programming Language :: Python
Classifier: Programming Language :: Python :: 3.8
Classifier: Programming Language :: Python :: 3.9
Classifier: Programming Language :: Python :: 3.10
Requires-Python: >=3.8
License-File: LICENSE.md
Requires-Dist: numpy
Provides-Extra: dev
Requires-Dist: pytest ; extra == 'dev'
Requires-Dist: black ; extra == 'dev'
Requires-Dist: pylint ; extra == 'dev'
